Compiled from "AuthTestCases.java"
public class testcode.authclient.AuthTestCases {
  static java.security.SecureRandom secureRandomGenerator;

  public testcode.authclient.AuthTestCases();
    Code:
       0: aload_0
       1: invokespecial #1                  // Method java/lang/Object."<init>":()V
       4: return

  public static void passwordPossiblyNotErased();
    Code:
       0: new           #2                  // class com/nimbusds/oauth2/sdk/auth/Secret
       3: dup
       4: ldc           #3                  // String foo
       6: invokespecial #4                  // Method com/nimbusds/oauth2/sdk/auth/Secret."<init>":(Ljava/lang/String;)V
       9: astore_0
      10: invokestatic  #5                  // Method randomCase:()Z
      13: ifeq          17
      16: return
      17: aload_0
      18: invokevirtual #6                  // Method com/nimbusds/oauth2/sdk/auth/Secret.getValue:()Ljava/lang/String;
      21: invokestatic  #7                  // Method com/nimbusds/oauth2/sdk/util/StringUtils.isBlank:(Ljava/lang/CharSequence;)Z
      24: ifeq          28
      27: return
      28: aload_0
      29: invokevirtual #8                  // Method com/nimbusds/oauth2/sdk/auth/Secret.erase:()V
      32: return

  public static void OK_passwordPossiblyNotErased();
    Code:
       0: new           #2                  // class com/nimbusds/oauth2/sdk/auth/Secret
       3: dup
       4: ldc           #3                  // String foo
       6: invokespecial #4                  // Method com/nimbusds/oauth2/sdk/auth/Secret."<init>":(Ljava/lang/String;)V
       9: astore_0
      10: invokestatic  #5                  // Method randomCase:()Z
      13: ifeq          21
      16: aload_0
      17: invokevirtual #8                  // Method com/nimbusds/oauth2/sdk/auth/Secret.erase:()V
      20: return
      21: aload_0
      22: invokevirtual #6                  // Method com/nimbusds/oauth2/sdk/auth/Secret.getValue:()Ljava/lang/String;
      25: invokestatic  #7                  // Method com/nimbusds/oauth2/sdk/util/StringUtils.isBlank:(Ljava/lang/CharSequence;)Z
      28: ifeq          36
      31: aload_0
      32: invokevirtual #8                  // Method com/nimbusds/oauth2/sdk/auth/Secret.erase:()V
      35: return
      36: aload_0
      37: invokevirtual #8                  // Method com/nimbusds/oauth2/sdk/auth/Secret.erase:()V
      40: return

  public static boolean randomCase();
    Code:
       0: getstatic     #9                  // Field secureRandomGenerator:Ljava/security/SecureRandom;
       3: invokevirtual #10                 // Method java/security/SecureRandom.nextInt:()I
       6: i2d
       7: ldc2_w        #11                 // double 0.5d
      10: dcmpl
      11: ifle          18
      14: iconst_1
      15: goto          19
      18: iconst_0
      19: ireturn

  public static void OK_passwordPossiblyNotErasedBecauseOfException_1();
    Code:
       0: new           #2                  // class com/nimbusds/oauth2/sdk/auth/Secret
       3: dup
       4: ldc           #3                  // String foo
       6: invokespecial #4                  // Method com/nimbusds/oauth2/sdk/auth/Secret."<init>":(Ljava/lang/String;)V
       9: astore_0
      10: invokestatic  #13                 // Method randomlyThrowException:()V
      13: new           #14                 // class java/lang/NullPointerException
      16: dup
      17: ldc           #15                 // String EE
      19: invokespecial #16                 // Method java/lang/NullPointerException."<init>":(Ljava/lang/String;)V
      22: athrow
      23: astore_1
      24: aload_1
      25: invokevirtual #17                 // Method java/lang/NullPointerException.printStackTrace:()V
      28: aload_0
      29: invokevirtual #8                  // Method com/nimbusds/oauth2/sdk/auth/Secret.erase:()V
      32: goto          42
      35: astore_2
      36: aload_0
      37: invokevirtual #8                  // Method com/nimbusds/oauth2/sdk/auth/Secret.erase:()V
      40: aload_2
      41: athrow
      42: return
    Exception table:
       from    to  target type
          10    23    23   Class java/lang/NullPointerException
          10    28    35   any

  public static void passwordPossiblyNotErasedBecauseOfCheckedException();
    Code:
       0: new           #2                  // class com/nimbusds/oauth2/sdk/auth/Secret
       3: dup
       4: ldc           #3                  // String foo
       6: invokespecial #4                  // Method com/nimbusds/oauth2/sdk/auth/Secret."<init>":(Ljava/lang/String;)V
       9: astore_0
      10: invokestatic  #18                 // Method randomlyThrowExceptionCheck:()V
      13: aload_0
      14: invokevirtual #8                  // Method com/nimbusds/oauth2/sdk/auth/Secret.erase:()V
      17: goto          30
      20: astore_0
      21: new           #20                 // class java/lang/RuntimeException
      24: dup
      25: aload_0
      26: invokespecial #21                 // Method java/lang/RuntimeException."<init>":(Ljava/lang/Throwable;)V
      29: athrow
      30: return
    Exception table:
       from    to  target type
           0    17    20   Class java/lang/Exception

  public static void OK_passwordPossiblyNotErasedBecauseOfException_2();
    Code:
       0: aconst_null
       1: astore_0
       2: new           #2                  // class com/nimbusds/oauth2/sdk/auth/Secret
       5: dup
       6: ldc           #3                  // String foo
       8: invokespecial #4                  // Method com/nimbusds/oauth2/sdk/auth/Secret."<init>":(Ljava/lang/String;)V
      11: astore_0
      12: invokestatic  #13                 // Method randomlyThrowException:()V
      15: aload_0
      16: ifnull        37
      19: aload_0
      20: invokevirtual #8                  // Method com/nimbusds/oauth2/sdk/auth/Secret.erase:()V
      23: goto          37
      26: astore_1
      27: aload_0
      28: ifnull        35
      31: aload_0
      32: invokevirtual #8                  // Method com/nimbusds/oauth2/sdk/auth/Secret.erase:()V
      35: aload_1
      36: athrow
      37: return
    Exception table:
       from    to  target type
           2    15    26   any

  public static void notStrongEnoughtStatusCodeChecking();
    Code:
       0: invokestatic  #23                 // Method createStatusCode:()I
       3: istore_0
       4: iload_0
       5: sipush        401
       8: if_icmpeq     18
      11: iload_0
      12: sipush        402
      15: if_icmpne     26
      18: new           #20                 // class java/lang/RuntimeException
      21: dup
      22: invokespecial #22                 // Method java/lang/RuntimeException."<init>":()V
      25: athrow
      26: return

  static {};
    Code:
       0: ldc           #24                 // String SHA1PRNG
       2: ldc           #25                 // String SUN
       4: invokestatic  #26                 // Method java/security/SecureRandom.getInstance:(Ljava/lang/String;Ljava/lang/String;)Ljava/security/SecureRandom;
       7: putstatic     #9                  // Field secureRandomGenerator:Ljava/security/SecureRandom;
      10: goto          18
      13: astore_0
      14: aload_0
      15: invokevirtual #29                 // Method java/security/GeneralSecurityException.printStackTrace:()V
      18: return
    Exception table:
       from    to  target type
           0    10    13   Class java/security/NoSuchAlgorithmException
           0    10    13   Class java/security/NoSuchProviderException