  public javax.ws.rs.core.Response validateTokens(com.google.api.client.auth.openidconnect.IdTokenResponse, testcode.oidc.util.googleapiclient.OidcConfig);
    Code:
       0: aload_1
       1: invokevirtual #42                 // Method com/google/api/client/auth/openidconnect/IdTokenResponse.parseIdToken:()Lcom/google/api/client/auth/openidconnect/IdToken;
       4: astore_3
       5: aload_2
       6: getfield      #48                 // Field testcode/oidc/util/googleapiclient/OidcConfig.nonce:Ljava/lang/String;
       9: aload_3
      10: invokevirtual #49                 // Method com/google/api/client/auth/openidconnect/IdToken.getPayload:()Lcom/google/api/client/auth/openidconnect/IdToken$Payload;
      13: invokevirtual #50                 // Method com/google/api/client/auth/openidconnect/IdToken$Payload.getNonce:()Ljava/lang/String;
      16: invokevirtual #25                 // Method java/lang/String.equals:(Ljava/lang/Object;)Z
      19: ifne          37
      22: getstatic     #14                 // Field javax/ws/rs/core/Response$Status.UNAUTHORIZED:Ljavax/ws/rs/core/Response$Status;
      25: invokestatic  #15                 // Method javax/ws/rs/core/Response.status:(Ljavax/ws/rs/core/Response$Status;)Ljavax/ws/rs/core/Response$ResponseBuilder;
      28: ldc           #51                 // String The provided nonce did not match the one saved from the authorization request.
      30: invokevirtual #21                 // Method javax/ws/rs/core/Response$ResponseBuilder.entity:(Ljava/lang/Object;)Ljavax/ws/rs/core/Response$ResponseBuilder;
      33: invokevirtual #22                 // Method javax/ws/rs/core/Response$ResponseBuilder.build:()Ljavax/ws/rs/core/Response;
      36: areturn
      37: aload_3
      38: aload_0
      39: getfield      #52                 // Field providerMetadata:Ljava/util/Map;
      42: ldc           #53                 // String key
      44: invokeinterface #54,  2           // InterfaceMethod java/util/Map.get:(Ljava/lang/Object;)Ljava/lang/Object;
      49: checkcast     #55                 // class java/security/PublicKey
      52: invokevirtual #56                 // Method com/google/api/client/auth/openidconnect/IdToken.verifySignature:(Ljava/security/PublicKey;)Z
      55: ifne          73
      58: getstatic     #14                 // Field javax/ws/rs/core/Response$Status.UNAUTHORIZED:Ljavax/ws/rs/core/Response$Status;
      61: invokestatic  #15                 // Method javax/ws/rs/core/Response.status:(Ljavax/ws/rs/core/Response$Status;)Ljavax/ws/rs/core/Response$ResponseBuilder;
      64: ldc           #57                 // String The jwt signature is not valid.
      66: invokevirtual #21                 // Method javax/ws/rs/core/Response$ResponseBuilder.entity:(Ljava/lang/Object;)Ljavax/ws/rs/core/Response$ResponseBuilder;
      69: invokevirtual #22                 // Method javax/ws/rs/core/Response$ResponseBuilder.build:()Ljavax/ws/rs/core/Response;
      72: areturn
      73: aload_3
      74: aload_0
      75: getfield      #58                 // Field config:Ljava/util/Properties;
      78: ldc           #59                 // String clientId
      80: invokevirtual #60                 // Method java/util/Properties.getProperty:(Ljava/lang/String;)Ljava/lang/String;
      83: invokestatic  #61                 // Method java/util/Collections.singleton:(Ljava/lang/Object;)Ljava/util/Set;
      86: invokevirtual #62                 // Method com/google/api/client/auth/openidconnect/IdToken.verifyAudience:(Ljava/util/Collection;)Z
      89: ifne          107
      92: getstatic     #14                 // Field javax/ws/rs/core/Response$Status.UNAUTHORIZED:Ljavax/ws/rs/core/Response$Status;
      95: invokestatic  #15                 // Method javax/ws/rs/core/Response.status:(Ljavax/ws/rs/core/Response$Status;)Ljavax/ws/rs/core/Response$ResponseBuilder;
      98: ldc           #63                 // String This request does not seem like it was meant for this audience.
     100: invokevirtual #21                 // Method javax/ws/rs/core/Response$ResponseBuilder.entity:(Ljava/lang/Object;)Ljavax/ws/rs/core/Response$ResponseBuilder;
     103: invokevirtual #22                 // Method javax/ws/rs/core/Response$ResponseBuilder.build:()Ljavax/ws/rs/core/Response;
     106: areturn
     107: aload_3
     108: invokestatic  #64                 // Method java/time/Instant.now:()Ljava/time/Instant;
     111: invokevirtual #65                 // Method java/time/Instant.toEpochMilli:()J
     114: ldc2_w        #67                 // long 300l
     117: invokevirtual #69                 // Method com/google/api/client/auth/openidconnect/IdToken.verifyExpirationTime:(JJ)Z
     120: ifne          138
     123: getstatic     #14                 // Field javax/ws/rs/core/Response$Status.UNAUTHORIZED:Ljavax/ws/rs/core/Response$Status;
     126: invokestatic  #15                 // Method javax/ws/rs/core/Response.status:(Ljavax/ws/rs/core/Response$Status;)Ljavax/ws/rs/core/Response$ResponseBuilder;
     129: ldc           #70                 // String Token expired.
     131: invokevirtual #21                 // Method javax/ws/rs/core/Response$ResponseBuilder.entity:(Ljava/lang/Object;)Ljavax/ws/rs/core/Response$ResponseBuilder;
     134: invokevirtual #22                 // Method javax/ws/rs/core/Response$ResponseBuilder.build:()Ljavax/ws/rs/core/Response;
     137: areturn
     138: aload_3
     139: aload_0
     140: getfield      #52                 // Field providerMetadata:Ljava/util/Map;
     143: ldc           #71                 // String issuer
     145: invokeinterface #54,  2           // InterfaceMethod java/util/Map.get:(Ljava/lang/Object;)Ljava/lang/Object;
     150: invokestatic  #72                 // Method java/lang/String.valueOf:(Ljava/lang/Object;)Ljava/lang/String;
     153: invokevirtual #73                 // Method com/google/api/client/auth/openidconnect/IdToken.verifyIssuer:(Ljava/lang/String;)Z
     156: ifne          174
     159: getstatic     #14                 // Field javax/ws/rs/core/Response$Status.UNAUTHORIZED:Ljavax/ws/rs/core/Response$Status;
     162: invokestatic  #15                 // Method javax/ws/rs/core/Response.status:(Ljavax/ws/rs/core/Response$Status;)Ljavax/ws/rs/core/Response$ResponseBuilder;
     165: ldc           #74                 // String The expected issuer did not match.
     167: invokevirtual #21                 // Method javax/ws/rs/core/Response$ResponseBuilder.entity:(Ljava/lang/Object;)Ljavax/ws/rs/core/Response$ResponseBuilder;
     170: invokevirtual #22                 // Method javax/ws/rs/core/Response$ResponseBuilder.build:()Ljavax/ws/rs/core/Response;
     173: areturn
     174: aload_0
     175: getfield      #28                 // Field authorizationCodeFlow:Lcom/google/api/client/auth/oauth2/AuthorizationCodeFlow;
     178: aload_1
     179: aload_2
     180: getfield      #44                 // Field testcode/oidc/util/googleapiclient/OidcConfig.appuuid:Ljava/util/UUID;
     183: invokevirtual #45                 // Method java/util/UUID.toString:()Ljava/lang/String;
     186: invokevirtual #46                 // Method com/google/api/client/auth/oauth2/AuthorizationCodeFlow.createAndStoreCredential:(Lcom/google/api/client/auth/oauth2/TokenResponse;Ljava/lang/String;)Lcom/google/api/client/auth/oauth2/Credential;
     189: pop
     190: invokestatic  #47                 // Method javax/ws/rs/core/Response.ok:()Ljavax/ws/rs/core/Response$ResponseBuilder;
     193: aload_1
     194: invokevirtual #21                 // Method javax/ws/rs/core/Response$ResponseBuilder.entity:(Ljava/lang/Object;)Ljavax/ws/rs/core/Response$ResponseBuilder;
     197: invokevirtual #22                 // Method javax/ws/rs/core/Response$ResponseBuilder.build:()Ljavax/ws/rs/core/Response;
     200: areturn
     201: astore_3
     202: getstatic     #78                 // Field javax/ws/rs/core/Response$Status.BAD_REQUEST:Ljavax/ws/rs/core/Response$Status;
     205: invokestatic  #15                 // Method javax/ws/rs/core/Response.status:(Ljavax/ws/rs/core/Response$Status;)Ljavax/ws/rs/core/Response$ResponseBuilder;
     208: invokevirtual #22                 // Method javax/ws/rs/core/Response$ResponseBuilder.build:()Ljavax/ws/rs/core/Response;
     211: areturn
     212: astore_3
     213: getstatic     #79                 // Field javax/ws/rs/core/Response$Status.INTERNAL_SERVER_ERROR:Ljavax/ws/rs/core/Response$Status;
     216: invokestatic  #15                 // Method javax/ws/rs/core/Response.status:(Ljavax/ws/rs/core/Response$Status;)Ljavax/ws/rs/core/Response$ResponseBuilder;
     219: invokevirtual #22                 // Method javax/ws/rs/core/Response$ResponseBuilder.build:()Ljavax/ws/rs/core/Response;
     222: areturn
    Exception table:
       from    to  target type
           0    36   201   Class java/io/IOException
           0    36   201   Class java/security/GeneralSecurityException
           0    36   201   Class java/lang/ClassCastException
          37    72   201   Class java/io/IOException
          37    72   201   Class java/security/GeneralSecurityException
          37    72   201   Class java/lang/ClassCastException
          73   106   201   Class java/io/IOException
          73   106   201   Class java/security/GeneralSecurityException
          73   106   201   Class java/lang/ClassCastException
         107   137   201   Class java/io/IOException
         107   137   201   Class java/security/GeneralSecurityException
         107   137   201   Class java/lang/ClassCastException
         138   173   201   Class java/io/IOException
         138   173   201   Class java/security/GeneralSecurityException
         138   173   201   Class java/lang/ClassCastException
         174   200   201   Class java/io/IOException
         174   200   201   Class java/security/GeneralSecurityException
         174   200   201   Class java/lang/ClassCastException
           0    36   212   Class java/lang/Exception
          37    72   212   Class java/lang/Exception
          73   106   212   Class java/lang/Exception
         107   137   212   Class java/lang/Exception
         138   173   212   Class java/lang/Exception
         174   200   212   Class java/lang/Exception
}
