Compiled from "OidcAuthenticationRequestStateUsageGoogle.java"
public class testcode.oidc.googleapiclient.OidcAuthenticationRequestStateUsageGoogle {
  java.security.SecureRandom secureRandom;

  public testcode.oidc.googleapiclient.OidcAuthenticationRequestStateUsageGoogle();
    Code:
       0: aload_0
       1: invokespecial #1                  // Method java/lang/Object."<init>":()V
       4: aload_0
       5: ldc           #2                  // String https://accounts.google.com/.well-known/openid-configuration
       7: putfield      #3                  // Field discoveryUri:Ljava/lang/String;
      10: aload_0
      11: ldc           #4                  // String https://client.com/callback
      13: putfield      #5                  // Field redirectUri:Ljava/lang/String;
      16: return

  public javax.ws.rs.core.Response exampleAuthenticationRequestForgetAddState(javax.servlet.http.HttpServletRequest, javax.servlet.http.HttpServletResponse);
    Code:
       0: aload_0
       1: new           #13                 // class com/google/api/client/auth/oauth2/AuthorizationCodeFlow$Builder
       4: dup
       5: invokestatic  #14                 // Method com/google/api/client/auth/oauth2/BearerToken.authorizationHeaderAccessMethod:()Lcom/google/api/client/auth/oauth2/Credential$AccessMethod;
       8: new           #15                 // class com/google/api/client/http/javanet/NetHttpTransport
      11: dup
      12: invokespecial #16                 // Method com/google/api/client/http/javanet/NetHttpTransport."<init>":()V
      15: new           #17                 // class com/google/api/client/testing/json/MockJsonFactory
      18: dup
      19: invokespecial #18                 // Method com/google/api/client/testing/json/MockJsonFactory."<init>":()V
      22: new           #19                 // class com/google/api/client/http/GenericUrl
      25: dup
      26: ldc           #20                 // String https://server.example.com/token
      28: invokespecial #21                 // Method com/google/api/client/http/GenericUrl."<init>":(Ljava/lang/String;)V
      31: new           #22                 // class com/google/api/client/http/BasicAuthentication
      34: dup
      35: aload_0
      36: getfield      #23                 // Field config:Ljava/util/Properties;
      39: ldc           #24                 // String clientId
      41: invokevirtual #25                 // Method java/util/Properties.getProperty:(Ljava/lang/String;)Ljava/lang/String;
      44: aload_0
      45: getfield      #23                 // Field config:Ljava/util/Properties;
      48: ldc           #26                 // String clientSecret
      50: invokevirtual #25                 // Method java/util/Properties.getProperty:(Ljava/lang/String;)Ljava/lang/String;
      53: invokespecial #27                 // Method com/google/api/client/http/BasicAuthentication."<init>":(Ljava/lang/String;Ljava/lang/String;)V
      56: aload_0
      57: getfield      #23                 // Field config:Ljava/util/Properties;
      60: ldc           #24                 // String clientId
      62: invokevirtual #25                 // Method java/util/Properties.getProperty:(Ljava/lang/String;)Ljava/lang/String;
      65: ldc           #28                 // String https://server.example.com/authorize
      67: invokespecial #29                 // Method com/google/api/client/auth/oauth2/AuthorizationCodeFlow$Builder."<init>":(Lcom/google/api/client/auth/oauth2/Credential$AccessMethod;Lcom/google/api/client/http/HttpTransport;Lcom/google/api/client/json/JsonFactory;Lcom/google/api/client/http/GenericUrl;Lcom/google/api/client/http/HttpExecuteInterceptor;Ljava/lang/String;Ljava/lang/String;)V
      70: new           #30                 // class com/google/api/client/util/store/FileDataStoreFactory
      73: dup
      74: new           #31                 // class java/io/File
      77: dup
      78: ldc           #32                 // String datastoredir
      80: invokespecial #33                 // Method java/io/File."<init>":(Ljava/lang/String;)V
      83: invokespecial #34                 // Method com/google/api/client/util/store/FileDataStoreFactory."<init>":(Ljava/io/File;)V
      86: invokestatic  #35                 // Method com/google/api/client/auth/oauth2/StoredCredential.getDefaultDataStore:(Lcom/google/api/client/util/store/DataStoreFactory;)Lcom/google/api/client/util/store/DataStore;
      89: invokevirtual #36                 // Method com/google/api/client/auth/oauth2/AuthorizationCodeFlow$Builder.setCredentialDataStore:(Lcom/google/api/client/util/store/DataStore;)Lcom/google/api/client/auth/oauth2/AuthorizationCodeFlow$Builder;
      92: invokevirtual #37                 // Method com/google/api/client/auth/oauth2/AuthorizationCodeFlow$Builder.build:()Lcom/google/api/client/auth/oauth2/AuthorizationCodeFlow;
      95: putfield      #38                 // Field authorizationCodeFlow:Lcom/google/api/client/auth/oauth2/AuthorizationCodeFlow;
      98: aload_0
      99: aload_0
     100: getfield      #38                 // Field authorizationCodeFlow:Lcom/google/api/client/auth/oauth2/AuthorizationCodeFlow;
     103: invokevirtual #39                 // Method com/google/api/client/auth/oauth2/AuthorizationCodeFlow.newAuthorizationUrl:()Lcom/google/api/client/auth/oauth2/AuthorizationCodeRequestUrl;
     106: ldc           #40                 // String code
     108: invokestatic  #41                 // Method java/util/Collections.singleton:(Ljava/lang/Object;)Ljava/util/Set;
     111: invokevirtual #42                 // Method com/google/api/client/auth/oauth2/AuthorizationCodeRequestUrl.setResponseTypes:(Ljava/util/Collection;)Lcom/google/api/client/auth/oauth2/AuthorizationCodeRequestUrl;
     114: iconst_4
     115: anewarray     #8                  // class java/lang/String
     118: dup
     119: iconst_0
     120: ldc           #43                 // String openid
     122: aastore
     123: dup
     124: iconst_1
     125: ldc           #44                 // String email
     127: aastore
     128: dup
     129: iconst_2
     130: ldc           #45                 // String profile
     132: aastore
     133: dup
     134: iconst_3
     135: ldc           #46                 // String address
     137: aastore
     138: invokestatic  #47                 // Method java/util/Arrays.asList:([Ljava/lang/Object;)Ljava/util/List;
     141: invokevirtual #48                 // Method com/google/api/client/auth/oauth2/AuthorizationCodeRequestUrl.setScopes:(Ljava/util/Collection;)Lcom/google/api/client/auth/oauth2/AuthorizationCodeRequestUrl;
     144: ldc           #4                  // String https://client.com/callback
     146: invokevirtual #49                 // Method com/google/api/client/auth/oauth2/AuthorizationCodeRequestUrl.setRedirectUri:(Ljava/lang/String;)Lcom/google/api/client/auth/oauth2/AuthorizationCodeRequestUrl;
     149: ldc           #50                 // String login_hint
     151: aload_1
     152: ldc           #50                 // String login_hint
     154: invokeinterface #51,  2           // InterfaceMethod javax/servlet/http/HttpServletRequest.getParameter:(Ljava/lang/String;)Ljava/lang/String;
     159: invokevirtual #52                 // Method com/google/api/client/auth/oauth2/AuthorizationCodeRequestUrl.set:(Ljava/lang/String;Ljava/lang/Object;)Lcom/google/api/client/auth/oauth2/AuthorizationCodeRequestUrl;
     162: putfield      #53                 // Field requestUrl:Lcom/google/api/client/auth/oauth2/AuthorizationCodeRequestUrl;
     165: aload_0
     166: getfield      #53                 // Field requestUrl:Lcom/google/api/client/auth/oauth2/AuthorizationCodeRequestUrl;
     169: invokevirtual #54                 // Method com/google/api/client/auth/oauth2/AuthorizationCodeRequestUrl.toURI:()Ljava/net/URI;
     172: invokestatic  #55                 // Method javax/ws/rs/core/Response.seeOther:(Ljava/net/URI;)Ljavax/ws/rs/core/Response$ResponseBuilder;
     175: invokevirtual #56                 // Method javax/ws/rs/core/Response$ResponseBuilder.build:()Ljavax/ws/rs/core/Response;
     178: areturn
     179: astore_3
     180: getstatic     #58                 // Field javax/ws/rs/core/Response$Status.UNAUTHORIZED:Ljavax/ws/rs/core/Response$Status;
     183: invokestatic  #59                 // Method javax/ws/rs/core/Response.status:(Ljavax/ws/rs/core/Response$Status;)Ljavax/ws/rs/core/Response$ResponseBuilder;
     186: invokevirtual #56                 // Method javax/ws/rs/core/Response$ResponseBuilder.build:()Ljavax/ws/rs/core/Response;
     189: areturn
    Exception table:
       from    to  target type
           0   178   179   Class java/lang/Exception

     public javax.ws.rs.core.Response validateTokens(com.google.api.client.auth.openidconnect.IdTokenResponse, javax.servlet.http.HttpSession) throws java.io.IOException, java.security.GeneralSecurityException;
        Code:
           1: invokevirtual #68                 // Method com/google/api/client/auth/openidconnect/IdTokenResponse.parseIdToken:()Lcom/google/api/client/auth/openidconnect/IdToken;
           6: ldc           #65                 // String nonce
           8: invokeinterface #69,  2           // InterfaceMethod javax/servlet/http/HttpSession.getAttribute:(Ljava/lang/String;)Ljava/lang/Object;
          13: aload_3
          14: invokevirtual #70                 // Method com/google/api/client/auth/openidconnect/IdToken.getPayload:()Lcom/google/api/client/auth/openidconnect/IdToken$Payload;
          17: invokevirtual #71                 // Method com/google/api/client/auth/openidconnect/IdToken$Payload.getNonce:()Ljava/lang/String;
          20: invokevirtual #72                 // Method java/lang/Object.equals:(Ljava/lang/Object;)Z
          23: ifne          41
          26: getstatic     #58                 // Field javax/ws/rs/core/Response$Status.UNAUTHORIZED:Ljavax/ws/rs/core/Response$Status;
          29: invokestatic  #59                 // Method javax/ws/rs/core/Response.status:(Ljavax/ws/rs/core/Response$Status;)Ljavax/ws/rs/core/Response$ResponseBuilder;
          32: ldc           #73                 // String The provided nonce did not match the one saved from the authorization request.
          40: areturn
          43: getfield      #75                 // Field keyFromDiscoveryDocument:Ljava/security/PublicKey;
          46: invokevirtual #76                 // Method com/google/api/client/auth/openidconnect/IdToken.verifySignature:(Ljava/security/PublicKey;)Z
          49: ifne          67
          52: getstatic     #58                 // Field javax/ws/rs/core/Response$Status.UNAUTHORIZED:Ljavax/ws/rs/core/Response$Status;
          55: invokestatic  #59                 // Method javax/ws/rs/core/Response.status:(Ljavax/ws/rs/core/Response$Status;)Ljavax/ws/rs/core/Response$ResponseBuilder;
          58: ldc           #77                 // String The jwt signature is not valid.
          80: invokevirtual #78                 // Method com/google/api/client/auth/openidconnect/IdToken.verifyAudience:(Ljava/util/Collection;)Z
          83: ifne          101
          86: getstatic     #58                 // Field javax/ws/rs/core/Response$Status.UNAUTHORIZED:Ljavax/ws/rs/core/Response$Status;
          89: invokestatic  #59                 // Method javax/ws/rs/core/Response.status:(Ljavax/ws/rs/core/Response$Status;)Ljavax/ws/rs/core/Response$ResponseBuilder;
          92: ldc           #79                 // String This request does not seem like it was meant for this audience.
         100: areturn
         111: invokevirtual #85                 // Method com/google/api/client/auth/openidconnect/IdToken.verifyExpirationTime:(JJ)Z
         114: ifne          132
         117: getstatic     #58                 // Field javax/ws/rs/core/Response$Status.UNAUTHORIZED:Ljavax/ws/rs/core/Response$Status;
         123: ldc           #86                 // String Token expired.
         131: areturn

         148: invokevirtual #87                 // Method com/google/api/client/auth/oauth2/AuthorizationCodeFlow.createAndStoreCredential:(Lcom/google/api/client/auth/oauth2/TokenResponse;
                                                    Ljava/lang/String;)Lcom/google/api/client/auth/oauth2/Credential;
         151: astore        4
         153: invokestatic  #88                 // Method javax/ws/rs/core/Response.ok:()Ljavax/ws/rs/core/Response$ResponseBuilder;
         157: invokevirtual #74                 // Method javax/ws/rs/core/Response$ResponseBuilder.entity:(Ljava/lang/Object;)Ljavax/ws/rs/core/Response$ResponseBuilder;
         160: invokevirtual #56                 // Method javax/ws/rs/core/Response$ResponseBuilder.build:()Ljavax/ws/rs/core/Response;
         163: areturn


  public javax.ws.rs.core.Response OK_exampleAuthenticationRequestAddState(javax.servlet.http.HttpServletRequest);
    Code:
       0: aload_0
       1: invokespecial #12                 // Method nonce:()Ljava/lang/String;
       4: astore_2
       5: aload_0
       6: invokespecial #60                 // Method state:()Ljava/lang/String;
       9: astore_3
      10: invokestatic  #61                 // Method java/util/UUID.randomUUID:()Ljava/util/UUID;
      13: astore        4
      15: aload_1
      16: invokeinterface #62,  1           // InterfaceMethod javax/servlet/http/HttpServletRequest.getSession:()Ljavax/servlet/http/HttpSession;
      21: ldc           #63                 // String state
      23: aload_2
      24: invokeinterface #64,  3           // InterfaceMethod javax/servlet/http/HttpSession.setAttribute:(Ljava/lang/String;Ljava/lang/Object;)V
      29: aload_1
      30: invokeinterface #62,  1           // InterfaceMethod javax/servlet/http/HttpServletRequest.getSession:()Ljavax/servlet/http/HttpSession;
      35: ldc           #65                 // String nonce
      37: aload_3
      38: invokeinterface #64,  3           // InterfaceMethod javax/servlet/http/HttpSession.setAttribute:(Ljava/lang/String;Ljava/lang/Object;)V
      43: aload_1
      44: invokeinterface #62,  1           // InterfaceMethod javax/servlet/http/HttpServletRequest.getSession:()Ljavax/servlet/http/HttpSession;
      49: ldc           #66                 // String userid
      51: aload         4
      53: invokeinterface #64,  3           // InterfaceMethod javax/servlet/http/HttpSession.setAttribute:(Ljava/lang/String;Ljava/lang/Object;)V
      58: aload_0
      59: new           #13                 // class com/google/api/client/auth/oauth2/AuthorizationCodeFlow$Builder
      62: dup
      63: invokestatic  #14                 // Method com/google/api/client/auth/oauth2/BearerToken.authorizationHeaderAccessMethod:()Lcom/google/api/client/auth/oauth2/Credential$AccessMethod;
      66: new           #15                 // class com/google/api/client/http/javanet/NetHttpTransport
      69: dup
      70: invokespecial #16                 // Method com/google/api/client/http/javanet/NetHttpTransport."<init>":()V
      73: new           #17                 // class com/google/api/client/testing/json/MockJsonFactory
      76: dup
      77: invokespecial #18                 // Method com/google/api/client/testing/json/MockJsonFactory."<init>":()V
      80: new           #19                 // class com/google/api/client/http/GenericUrl
      83: dup
      84: ldc           #20                 // String https://server.example.com/token
      86: invokespecial #21                 // Method com/google/api/client/http/GenericUrl."<init>":(Ljava/lang/String;)V
      89: new           #22                 // class com/google/api/client/http/BasicAuthentication
      92: dup
      93: aload_0
      94: getfield      #23                 // Field config:Ljava/util/Properties;
      97: ldc           #24                 // String clientId
      99: invokevirtual #25                 // Method java/util/Properties.getProperty:(Ljava/lang/String;)Ljava/lang/String;
     102: aload_0
     103: getfield      #23                 // Field config:Ljava/util/Properties;
     106: ldc           #26                 // String clientSecret
     108: invokevirtual #25                 // Method java/util/Properties.getProperty:(Ljava/lang/String;)Ljava/lang/String;
     111: invokespecial #27                 // Method com/google/api/client/http/BasicAuthentication."<init>":(Ljava/lang/String;Ljava/lang/String;)V
     114: aload_0
     115: getfield      #23                 // Field config:Ljava/util/Properties;
     118: ldc           #24                 // String clientId
     120: invokevirtual #25                 // Method java/util/Properties.getProperty:(Ljava/lang/String;)Ljava/lang/String;
     123: ldc           #28                 // String https://server.example.com/authorize
     125: invokespecial #29                 // Method com/google/api/client/auth/oauth2/AuthorizationCodeFlow$Builder."<init>":(Lcom/google/api/client/auth/oauth2/Credential$AccessMethod;Lcom/google/api/client/http/HttpTransport;Lcom/google/api/client/json/JsonFactory;Lcom/google/api/client/http/GenericUrl;Lcom/google/api/client/http/HttpExecuteInterceptor;Ljava/lang/String;Ljava/lang/String;)V
     128: invokevirtual #37                 // Method com/google/api/client/auth/oauth2/AuthorizationCodeFlow$Builder.build:()Lcom/google/api/client/auth/oauth2/AuthorizationCodeFlow;
     131: putfield      #38                 // Field authorizationCodeFlow:Lcom/google/api/client/auth/oauth2/AuthorizationCodeFlow;
     134: aload_0
     135: aload_0
     136: getfield      #38                 // Field authorizationCodeFlow:Lcom/google/api/client/auth/oauth2/AuthorizationCodeFlow;
     139: invokevirtual #39                 // Method com/google/api/client/auth/oauth2/AuthorizationCodeFlow.newAuthorizationUrl:()Lcom/google/api/client/auth/oauth2/AuthorizationCodeRequestUrl;
     142: ldc           #40                 // String code
     144: invokestatic  #41                 // Method java/util/Collections.singleton:(Ljava/lang/Object;)Ljava/util/Set;
     147: invokevirtual #42                 // Method com/google/api/client/auth/oauth2/AuthorizationCodeRequestUrl.setResponseTypes:(Ljava/util/Collection;)Lcom/google/api/client/auth/oauth2/AuthorizationCodeRequestUrl;
     150: iconst_4
     151: anewarray     #8                  // class java/lang/String
     154: dup
     155: iconst_0
     156: ldc           #43                 // String openid
     158: aastore
     159: dup
     160: iconst_1
     161: ldc           #44                 // String email
     163: aastore
     164: dup
     165: iconst_2
     166: ldc           #45                 // String profile
     168: aastore
     169: dup
     170: iconst_3
     171: ldc           #46                 // String address
     173: aastore
     174: invokestatic  #47                 // Method java/util/Arrays.asList:([Ljava/lang/Object;)Ljava/util/List;
     177: invokevirtual #48                 // Method com/google/api/client/auth/oauth2/AuthorizationCodeRequestUrl.setScopes:(Ljava/util/Collection;)Lcom/google/api/client/auth/oauth2/AuthorizationCodeRequestUrl;
     180: ldc           #4                  // String https://client.com/callback
     182: invokevirtual #49                 // Method com/google/api/client/auth/oauth2/AuthorizationCodeRequestUrl.setRedirectUri:(Ljava/lang/String;)Lcom/google/api/client/auth/oauth2/AuthorizationCodeRequestUrl;
     185: ldc           #50                 // String login_hint
     187: aload_1
     188: ldc           #50                 // String login_hint
     190: invokeinterface #51,  2           // InterfaceMethod javax/servlet/http/HttpServletRequest.getParameter:(Ljava/lang/String;)Ljava/lang/String;
     195: invokevirtual #52                 // Method com/google/api/client/auth/oauth2/AuthorizationCodeRequestUrl.set:(Ljava/lang/String;Ljava/lang/Object;)Lcom/google/api/client/auth/oauth2/AuthorizationCodeRequestUrl;
     198: aload_2
     199: invokevirtual #67                 // Method com/google/api/client/auth/oauth2/AuthorizationCodeRequestUrl.setState:(Ljava/lang/String;)Lcom/google/api/client/auth/oauth2/AuthorizationCodeRequestUrl;
     202: ldc           #65                 // String nonce
     204: aload_3
     205: invokevirtual #52                 // Method com/google/api/client/auth/oauth2/AuthorizationCodeRequestUrl.set:(Ljava/lang/String;Ljava/lang/Object;)Lcom/google/api/client/auth/oauth2/AuthorizationCodeRequestUrl;
     208: putfield      #53                 // Field requestUrl:Lcom/google/api/client/auth/oauth2/AuthorizationCodeRequestUrl;
     211: aload_0
     212: getfield      #53                 // Field requestUrl:Lcom/google/api/client/auth/oauth2/AuthorizationCodeRequestUrl;
     215: invokevirtual #54                 // Method com/google/api/client/auth/oauth2/AuthorizationCodeRequestUrl.toURI:()Ljava/net/URI;
     218: invokestatic  #55                 // Method javax/ws/rs/core/Response.seeOther:(Ljava/net/URI;)Ljavax/ws/rs/core/Response$ResponseBuilder;
     221: invokevirtual #56                 // Method javax/ws/rs/core/Response$ResponseBuilder.build:()Ljavax/ws/rs/core/Response;
     224: areturn
     225: astore_2
     226: getstatic     #58                 // Field javax/ws/rs/core/Response$Status.UNAUTHORIZED:Ljavax/ws/rs/core/Response$Status;
     229: invokestatic  #59                 // Method javax/ws/rs/core/Response.status:(Ljavax/ws/rs/core/Response$Status;)Ljavax/ws/rs/core/Response$ResponseBuilder;
     232: invokevirtual #56                 // Method javax/ws/rs/core/Response$ResponseBuilder.build:()Ljavax/ws/rs/core/Response;
     235: areturn
    Exception table:
       from    to  target type
           0   224   225   Class java/lang/Exception

  public javax.ws.rs.core.Response OK_exampleTokenRequestCheckState(javax.servlet.http.HttpServletRequest, javax.servlet.http.HttpServletResponse);
    Code:
       0: aload_0
      ...
      12: ldc           #89                 // String aud
      14: invokeinterface #51,  2           // InterfaceMethod javax/servlet/http/HttpServletRequest.getParameter:(Ljava/lang/String;)Ljava/lang/String;
      19: invokevirtual #90                 // Method java/lang/String.equals:(Ljava/lang/Object;)Z
      22: ifne          40
      25: getstatic     #58                 // Field javax/ws/rs/core/Response$Status.UNAUTHORIZED:Ljavax/ws/rs/core/Response$Status;
      28: invokestatic  #59                 // Method javax/ws/rs/core/Response.status:(Ljavax/ws/rs/core/Response$Status;)Ljavax/ws/rs/core/Response$ResponseBuilder;
      ...
      39: areturn
      40: aload_1
      41: invokeinterface #62,  1           // InterfaceMethod javax/servlet/http/HttpServletRequest.getSession:()Ljavax/servlet/http/HttpSession;
      46: ldc           #63                 // String state
      48: invokeinterface #69,  2           // InterfaceMethod javax/servlet/http/HttpSession.getAttribute:(Ljava/lang/String;)Ljava/lang/Object;
      53: aload_1
      54: ldc           #63                 // String state
      56: invokeinterface #51,  2           // InterfaceMethod javax/servlet/http/HttpServletRequest.getParameter:(Ljava/lang/String;)Ljava/lang/String;
      61: invokevirtual #72                 // Method java/lang/Object.equals:(Ljava/lang/Object;)Z
      64: ifeq          82
      67: getstatic     #58                 // Field javax/ws/rs/core/Response$Status.UNAUTHORIZED:Ljavax/ws/rs/core/Response$Status;
      73: ldc           #92                 // String The state does not match
      ...
      81: areturn
      98: invokevirtual #93                 // Method com/google/api/client/auth/oauth2/AuthorizationCodeFlow.newTokenRequest:(Ljava/lang/String;)Lcom/google/api/client/auth/oauth2/AuthorizationCodeTokenRequest;

     106: getfield      #38                 // Field authorizationCodeFlow:Lcom/google/api/client/auth/oauth2/AuthorizationCodeFlow;
     115: invokevirtual #95                 // Method com/google/api/client/auth/oauth2/AuthorizationCodeTokenRequest.setTokenServerUrl:(Lcom/google/api/client/http/GenericUrl;)
                                                Lcom/google/api/client/auth/oauth2/AuthorizationCodeTokenRequest;
     118: aload_0
     119: getfield      #38                 // Field authorizationCodeFlow:Lcom/google/api/client/auth/oauth2/AuthorizationCodeFlow;
     122: invokevirtual #96                 // Method com/google/api/client/auth/oauth2/AuthorizationCodeFlow.getClientAuthentication:()Lcom/google/api/client/http/HttpExecuteInterceptor;
     125: invokevirtual #97                 // Method com/google/api/client/auth/oauth2/AuthorizationCodeTokenRequest.setClientAuthentication:
                                                (Lcom/google/api/client/http/HttpExecuteInterceptor;)Lcom/google/api/client/auth/oauth2/AuthorizationCodeTokenRequest;
     132: invokevirtual #98                 // Method com/google/api/client/auth/oauth2/AuthorizationCodeTokenRequest.setRedirectUri:(Ljava/lang/String;)Lcom/google/api/client/auth/oauth2/AuthorizationCodeTokenRequest;
     139: invokestatic  #99                 // Method com/google/api/client/auth/openidconnect/IdTokenResponse.execute:(Lcom/google/api/client/auth/oauth2/TokenRequest;)Lcom/google/api/client/auth/openidconnect/IdTokenResponse;
     153: invokespecial #100                // Method validateTokens:(Lcom/google/api/client/auth/openidconnect/IdTokenResponse;Ljavax/servlet/http/HttpSession;)Ljavax/ws/rs/core/Response;
     156: areturn
     157: astore_3
     158: getstatic     #58                 // Field javax/ws/rs/core/Response$Status.UNAUTHORIZED:Ljavax/ws/rs/core/Response$Status;
     161: invokestatic  #59                 // Method javax/ws/rs/core/Response.status:(Ljavax/ws/rs/core/Response$Status;)Ljavax/ws/rs/core/Response$ResponseBuilder;
     164: invokevirtual #56                 // Method javax/ws/rs/core/Response$ResponseBuilder.build:()Ljavax/ws/rs/core/Response;
     167: areturn
}
